AUTHORS
ChangeLog
LICENSE
README.rst
ghcrypt.ini
requirements.txt
setup.cfg
setup.py
ghcrypt/__init__.py
ghcrypt/ghcrypt_main.py
ghcrypt.egg-info/PKG-INFO
ghcrypt.egg-info/SOURCES.txt
ghcrypt.egg-info/dependency_links.txt
ghcrypt.egg-info/entry_points.txt
ghcrypt.egg-info/not-zip-safe
ghcrypt.egg-info/pbr.json
ghcrypt.egg-info/requires.txt
ghcrypt.egg-info/top_level.txt