Metadata-Version: 1.0
Name: ghcrypt
Version: 0.0.6
Summary: Encrypt things for others using github keys.
Home-page: https://github.com/harlowja/cryptic
Author: Joshua Harlow
Author-email: harlowja@gmail.com
License: MIT
Platform: UNKNOWN
